cheggpy/__init__.py
cheggpy/__main__.py
cheggpy/custom_exceptions.py
cheggpy/login_util.py
cheggpy/logout_util.py
cheggpy/question.py
cheggpy/question_util.py
cheggpy/util.py
cheggpy/assets/notify.mp3
cheggpy-1.0.2.dist-info/LICENSE
cheggpy-1.0.2.dist-info/METADATA
cheggpy-1.0.2.dist-info/WHEEL
cheggpy-1.0.2.dist-info/entry_points.txt
cheggpy-1.0.2.dist-info/top_level.txt
cheggpy-1.0.2.dist-info/RECORD
