Metadata-Version: 2.1
Name: cheggpy
Version: 1.0.2
Summary: A Python package for interacting with the Chegg API for Chegg Experts
Author-email: Harrykp <chaudharyharshit9@gmail.com>
License: MIT License
Project-URL: Homepage, https://github.com/Harry-kp/cheggpy
Keywords: chegg,automation
Classifier: License :: OSI Approved :: MIT License
Classifier: Programming Language :: Python
Classifier: Programming Language :: Python :: 3
Requires-Python: >=3
License-File: LICENSE
Requires-Dist: bs4
Requires-Dist: requests
Requires-Dist: colorama
Requires-Dist: tqdm
Requires-Dist: tomli
Provides-Extra: dev
Requires-Dist: autopep8 ; extra == 'dev'
Requires-Dist: flake8 ; extra == 'dev'
Requires-Dist: portray ; extra == 'dev'
